kim_edn/__init__.py
kim_edn/_version.py
kim_edn/decoder.py
kim_edn/encoder.py
kim_edn/scanner.py
kim_edn/tool.py
kim_edn-1.4.0.dist-info/LICENSE
kim_edn-1.4.0.dist-info/METADATA
kim_edn-1.4.0.dist-info/WHEEL
kim_edn-1.4.0.dist-info/top_level.txt
kim_edn-1.4.0.dist-info/RECORD
