Metadata-Version: 2.1
Name: kim-edn
Version: 1.4.0
Summary: kim-edn - KIM-EDN encoder and decoder.
Author-email: Yaser Afshar <ya.afshar@gmail.com>
Maintainer-email: Yaser Afshar <ya.afshar@gmail.com>
Project-URL: Homepage, https://github.com/openkim/kim-edn
Project-URL: Issues, https://github.com/openkim/kim-edn/issues
Keywords: kim-edn,edn
Classifier: Development Status :: 5 - Production/Stable
Classifier: Intended Audience :: Science/Research
Classifier: Topic :: Scientific/Engineering
Classifier: Operating System :: OS Independent
Classifier: License :: OSI Approved :: GNU Lesser General Public License v2 or later (LGPLv2+)
Classifier: Programming Language :: Python :: 3
Requires-Python: >=3.8
License-File: LICENSE
